cmuseo/__init__.py
cmuseo/colormap.py
cmuseo-1.0.1.dist-info/licenses/LICENSE
cmuseo-1.0.1.dist-info/METADATA
cmuseo-1.0.1.dist-info/WHEEL
cmuseo-1.0.1.dist-info/top_level.txt
cmuseo-1.0.1.dist-info/RECORD
