Metadata-Version: 2.4
Name: cmuseo
Version: 1.0.1
Summary: Perceptually uniform colormaps for scientific visualization
Author-email: Oliver Schneising <schneising@iup.physik.uni-bremen.de>
License-Expression: GPL-3.0-only
Project-URL: Homepage, https://pypi.org/project/cmuseo/
Classifier: Programming Language :: Python :: 3
Classifier: Operating System :: OS Independent
Classifier: Intended Audience :: Science/Research
Classifier: Topic :: Scientific/Engineering :: Visualization
Requires-Python: >=3.7
License-File: LICENSE
Requires-Dist: matplotlib>=3.2
Dynamic: license-file
